{"books":{"831d982acab851540465417027":{"title":"1984","author":"Дж. Оруэлл","publication_date":"1949","image_url":"/public/images/1984.jpeg","reader":"Михаил","expiration_date":"1542229200000"},"278bd98077ad51540468089250":{"title":"О дивный новый мир","author":"Олдос Хаксли","publication_date":"1932","image_url":"/public/images/Хаксли.jpeg","reader":null,"expiration_date":null},"024859a0ed61c1540474773125":{"title":"Мы (Кто - мы?)","author":"Замятин Е.И.","publication_date":"1924","image_url":"/public/images/Мы.jpeg","reader":null,"expiration_date":null}}}